srlearn/BoostSRL.jar
srlearn/SRLBoost.jar
srlearn/__init__.py
srlearn/_meta.py
srlearn/auc.jar
srlearn/background.py
srlearn/base.py
srlearn/boostsrl.py
srlearn/database.py
srlearn/example_data.py
srlearn/plotting.py
srlearn/rdn.py
srlearn/system_manager.py
srlearn/datasets/__init__.py
srlearn/datasets/_toy_cancer.py
srlearn/datasets/_toy_father.py
srlearn/datasets/tests/__init__.py
srlearn/datasets/tests/test_toy_cancer.py
srlearn/datasets/tests/test_toy_father.py
srlearn/tests/__init__.py
srlearn/tests/test_background.py
srlearn/tests/test_base.py
srlearn/tests/test_database.py
srlearn/tests/test_plotting.py
srlearn/tests/test_rdn.py
srlearn/tests/test_rdn_feature_importances.py
srlearn/tests/test_serialize.py
srlearn/tests/test_system_manager.py
srlearn/tests/test_system_manager_reset.py
srlearn/utils/__init__.py
srlearn/utils/_parse_trees.py
srlearn/utils/_show_versions.py
srlearn/utils/tests/__init__.py
srlearn/utils/tests/test_parse_trees.py
srlearn/utils/tests/test_show_versions.py
srlearn-0.5.5.dist-info/LICENSE
srlearn-0.5.5.dist-info/METADATA
srlearn-0.5.5.dist-info/WHEEL
srlearn-0.5.5.dist-info/top_level.txt
srlearn-0.5.5.dist-info/RECORD
